{"_type": "SearchResponse", "webPages": {"webSearchUrl": "https:\/\/www.bing.com\/cr?IG=0E1F17A8DE2343DCB81E5D3743307894&CID=01B2A43517346081302FADF6162661E7&rd=1&h=QRj-1wJPZPdVlBA_xFshW3dIwgn0XZTHfbnRfuIESUk&v=1&r=https%3a%2f%2fwww.bing.com%2fsearch%3fq%3d%2522%25e4%25b8%258a%25e5%25ba%2595%2522&p=DevEx,5297.1", "totalEstimatedMatches": 39800, "value": [{"id": "https:\/\/api.cognitive.microsoft.com\/api\/v5\/#WebPages.0", "name": "台形 - Wikipedia", "url": "https:\/\/www.bing.com\/cr?IG=0E1F17A8DE2343DCB81E5D3743307894&CID=01B2A43517346081302FADF6162661E7&rd=1&h=fGCeu0aG5KFwV9wSZPAXNKker1sb7uOrEN8RKXafRno&v=1&r=https%3a%2f%2fja.wikipedia.org%2fwiki%2f%25E5%258F%25B0%25E5%25BD%25A2&p=DevEx,5085.1", "about": [{"name": "Trapezoid"}], "displayUrl": "https:\/\/ja.wikipedia.org\/wiki\/台形", "snippet": "台形（だいけい、米: trapezoid 、英: trapezium ）は、四角形の一部で、少なくとも一組の対辺が互いに平行であるような図形である。平行な2本の対辺を台形の底辺といい、そのうち一方を上底（じょうてい）、他方を下底（かてい）とよぶ。", "dateLastCrawled": "2016-10-24T10:31:00"}, {"id": "https:\/\/api.cognitive.microsoft.com\/api\/v5\/#WebPages.1", "name": "じょうてい【上底】の意味 - goo国語辞書", "url": "http:\/\/www.bing.com\/cr?IG=0E1F17A8DE2343DCB81E5D3743307894&CID=01B2A43517346081302FADF6162661E7&rd=1&h=a162WRk3nmNay_ZcGIbTnsdLBQlH4i30Svu5erOcyHY&v=1&r=http%3a%2f%2fdictionary.goo.ne.jp%2fjn%2f109424%2fmeaning%2fm0u%2f&p=DevEx,5097.1", "displayUrl": "dictionary.goo.ne.jp\/jn\/109424\/meaning\/m0u", "snippet": "じょうてい【上底】とは。意味や解説、類語。台形の平行な2辺のうち、上の辺。角錐台・円錐台では、上方の底面。⇔下底。 - goo国語辞書は27万語以上を収録。政治・経済・医学・ITなど、最新用語の追加も定期的に行っています。", "dateLastCrawled": "2016-10-23T17:45:00"}, {"id": "https:\/\/api.cognitive.microsoft.com\/api\/v5\/#WebPages.2", "name": "台形の面積を求める公式は(上底＋下底)×高さ ...- Yahoo!知恵袋", "url": "http:\/\/www.bing.com\/cr?IG=0E1F17A8DE2343DCB81E5D3743307894&CID=01B2A43517346081302FADF6162661E7&rd=1&h=hXP5byy-PQ5p3SvytXRar_kwyxQEUoY23w45499p6-Y&v=1&r=http%3a%2f%2fdetail.chiebukuro.yahoo.co.jp%2fqa%2fquestion_detail%2fq1263044867&p=DevEx,5111.1", "displayUrl": "detail.chiebukuro.yahoo.co.jp\/qa\/question_detail\/q1263044867", "snippet": "台形の面積を求める公式は (上底＋下底)×高さ÷2ですが、 ｢上の底｣って、なんか変じゃないですか？ (上辺＋底辺)×・・、なら納得できるのですが。 まぁ、語呂で憶えてるってのは、確かなんですが・・。", "dateLastCrawled": "2016-10-25T06:02:00"}, {"id": "https:\/\/api.cognitive.microsoft.com\/api\/v5\/#WebPages.3", "name": "上底とは - 「上底」の意味ならWeblio辞書", "url": "http:\/\/www.bing.com\/cr?IG=0E1F17A8DE2343DCB81E5D3743307894&CID=01B2A43517346081302FADF6162661E7&rd=1&h=hZFMDnQ7kvyAgNzrHhiYPH5mWr-nmAiGmFxQNWR4Z9M&v=1&r=http%3a%2f%2fwww.weblio.jp%2fcontent%2f%25E4%25B8%258A%25E5%25BA%2595&p=DevEx,5123.1", "displayUrl": "www.weblio.jp\/content\/上底", "snippet": "上底のお隣キーワード 上帝会 上席 上帯 上幕 上平 上床 上底 上座 上座石 上座部 上廻る 上弦 上張 英和和英テキスト翻訳 >> Weblio翻訳 英語⇒日本語 日本語⇒英語 検索ランキング 1～10位 11～20位 21～30位 痛み入ります 抽斗 ...", "dateLastCrawled": "2016-10-30T10:22:00"}, {"id": "https:\/\/api.cognitive.microsoft.com\/api\/v5\/#WebPages.4", "name": "上底の英語・英訳 - 英和辞典・和英辞典 Weblio辞書", "url": "http:\/\/www.bing.com\/cr?IG=0E1F17A8DE2343DCB81E5D3743307894&CID=01B2A43517346081302FADF6162661E7&rd=1&h=55pG_J-K_HUJi52vReucn6BRgQ1tk40oFS1BaVjyIxc&v=1&r=http%3a%2f%2fejje.weblio.jp%2fcontent%2f%25E4%25B8%258A%25E5%25BA%2595&p=DevEx,5135.1", "displayUrl": "ejje.weblio.jp\/content\/上底", "snippet": "上底を英語に訳すと 読み方：あげぞこ、あげそこ揚げ底、上底、揚底 とも書く(1)文法情報（名詞）対訳 false bottom; fake bottom; raised bottom; platform (shoes);... - 約1014万語ある英和辞典・和英辞典。発音・イディオムも分かる英語 ...", "dateLastCrawled": "2016-10-23T01:50:00"}, {"id": "https:\/\/api.cognitive.microsoft.com\/api\/v5\/#WebPages.5", "name": "★上底という表現は、いつ頃から使われたのでしょうか。 これ ...", "url": "http:\/\/www.bing.com\/cr?IG=0E1F17A8DE2343DCB81E5D3743307894&CID=01B2A43517346081302FADF6162661E7&rd=1&h=KeIUDkpam2qiY5wdKYLD1_pvW1UCwgYdue_kJ-c5Gkw&v=1&r=http%3a%2f%2fdetail.chiebukuro.yahoo.co.jp%2fqa%2fquestion_detail%2fq148930944&p=DevEx,5150.1", "displayUrl": "detail.chiebukuro.yahoo.co.jp\/qa\/question_detail\/q148930944", "snippet": "上底という表現は、いつ頃から使われたのでしょうか。 これはご存知、台形の面積の公式に関する質問です。 そこに上底と下底とありますよね。 下底については、小学生の時容易に理解出来たのですが、 上底という表現が ...", "dateLastCrawled": "2016-10-24T23:32:00"}, {"id": "https:\/\/api.cognitive.microsoft.com\/api\/v5\/#WebPages.6", "name": "上底と下底、高さから台形の面積を数学の公式で計算します。", "url": "http:\/\/www.bing.com\/cr?IG=0E1F17A8DE2343DCB81E5D3743307894&CID=01B2A43517346081302FADF6162661E7&rd=1&h=8eblA8f03-D0KRi556Phn7pAuMk70RTHhGZE12XWMHA&v=1&r=http%3a%2f%2fcalc-site.com%2fareas%2ftrapezoid&p=DevEx,5162.1", "displayUrl": "calc-site.com\/areas\/trapezoid", "snippet": "上底と下底と高さから台形の面積を公式を使って計算します。 上底a、下底b、高さhを入力し「台形の面積を計算」ボタンをクリックすると、上底と下底と高さから台形の面積を計算して表示します。", "dateLastCrawled": "2016-10-28T19:45:00"}, {"id": "https:\/\/api.cognitive.microsoft.com\/api\/v5\/#WebPages.7", "name": "上底の検索結果 - 辞書すべて - goo辞書", "url": "http:\/\/www.bing.com\/cr?IG=0E1F17A8DE2343DCB81E5D3743307894&CID=01B2A43517346081302FADF6162661E7&rd=1&h=wzEORDP5UkKT-uRscTMqd5MVpOo1tzfRmVJEVJtFCrE&v=1&r=http%3a%2f%2fdictionary.goo.ne.jp%2fsrch%2fall%2f%25E4%25B8%258A%25E5%25BA%2595%2fm0u%2f&p=DevEx,5174.1", "displayUrl": "dictionary.goo.ne.jp\/srch\/all\/上底\/m0u", "snippet": "上底で始まる言葉の辞書すべての検索結果。あげぞこ【上（げ）底】,じょうてい【上底】,あげぞこびん【上底壜】,うわそこぶきてんろ【上底吹転炉】,うわそこぶきてんろせいこう【上底吹転炉製鋼】 - goo辞書は無料で使える日本 ...", "dateLastCrawled": "2016-10-23T14:48:00"}, {"id": "https:\/\/api.cognitive.microsoft.com\/api\/v5\/#WebPages.8", "name": "上げ底・上底(あげぞこ)とは - コトバンク", "url": "https:\/\/www.bing.com\/cr?IG=0E1F17A8DE2343DCB81E5D3743307894&CID=01B2A43517346081302FADF6162661E7&rd=1&h=Qli8jwB6rDwMegRAeu6fY8fwGL7AbEAYYVEQ7tD-IpA&v=1&r=https%3a%2f%2fkotobank.jp%2fword%2f%25E4%25B8%258A%25E3%2581%2592%25E5%25BA%2595%25E3%2583%25BB%25E4%25B8%258A%25E5%25BA%2595-195406&p=DevEx,5186.1", "displayUrl": "https:\/\/kotobank.jp\/word\/上げ底・上底", "snippet": "大辞林 第三版 - 上げ底・上底の用語解説 - 箱・桶おけなどの底を上げて作ったもの。見かけに比べて中身が少ししか入らない。 「 －のみやげ物」 ... 出典｜三省堂 (C) Sanseido Co.,Ltd. 編者：松村明 ...", "dateLastCrawled": "2016-10-27T00:37:00"}, {"id": "https:\/\/api.cognitive.microsoft.com\/api\/v5\/#WebPages.9", "name": "「上底」に関連した英語例文の一覧 - Weblio英語例文検索", "url": "http:\/\/www.bing.com\/cr?IG=0E1F17A8DE2343DCB81E5D3743307894&CID=01B2A43517346081302FADF6162661E7&rd=1&h=vj3M82t8jQASRp6MlWX-uEHc04tb0QCk7AordhWa0qQ&v=1&r=http%3a%2f%2fejje.weblio.jp%2fsentence%2fcontent%2f%25E4%25B8%258A%25E5%25BA%2595&p=DevEx,5198.1", "displayUrl": "ejje.weblio.jp\/sentence\/content\/上底", "snippet": "各突起3の上底5には、上底側開口部の形状が多角形となるように、上底5から下底6の方向に向かって、打ち抜かれた開口部8が形成されている。 例文帳に追加 At the upper base 5 of each jut 3 is formed an opening part 8 punched ...", "dateLastCrawled": "2016-10-12T04:08:00"}]}, "relatedSearches": {"id": "https:\/\/api.cognitive.microsoft.com\/api\/v5\/#RelatedSearches", "value": [{"text": "上底 英語", "displayText": "上底 英語", "webSearchUrl": "https:\/\/www.bing.com\/cr?IG=0E1F17A8DE2343DCB81E5D3743307894&CID=01B2A43517346081302FADF6162661E7&rd=1&h=jGloz8oTwyPejUg9enTsj5h6045U7MYAUl7ft5lrC80&v=1&r=https%3a%2f%2fwww.bing.com%2fsearch%3fq%3d%25e4%25b8%258a%25e5%25ba%2595%2b%25e8%258b%25b1%25e8%25aa%259e&p=DevEx,5298.1"}, {"text": "中間市上底井野", "displayText": "中間市上底井野", "webSearchUrl": "https:\/\/www.bing.com\/cr?IG=0E1F17A8DE2343DCB81E5D3743307894&CID=01B2A43517346081302FADF6162661E7&rd=1&h=_PEhm5GtPG05ZMHRr4jkF9pqrpBRBJ1KLjJ7XFFjkrY&v=1&r=https%3a%2f%2fwww.bing.com%2fsearch%3fq%3d%25e4%25b8%25ad%25e9%2596%2593%25e5%25b8%2582%25e4%25b8%258a%25e5%25ba%2595%25e4%25ba%2595%25e9%2587%258e&p=DevEx,5299.1"}, {"text": "上底+下底", "displayText": "上底+下底", "webSearchUrl": "https:\/\/www.bing.com\/cr?IG=0E1F17A8DE2343DCB81E5D3743307894&CID=01B2A43517346081302FADF6162661E7&rd=1&h=dEyYnQWUT-xFiQkHj-OYZV4VoYguCoeTTuP5uO-lmo4&v=1&r=https%3a%2f%2fwww.bing.com%2fsearch%3fq%3d%25e4%25b8%258a%25e5%25ba%2595%252b%25e4%25b8%258b%25e5%25ba%2595&p=DevEx,5300.1"}, {"text": "台形 上底", "displayText": "台形 上底", "webSearchUrl": "https:\/\/www.bing.com\/cr?IG=0E1F17A8DE2343DCB81E5D3743307894&CID=01B2A43517346081302FADF6162661E7&rd=1&h=gvLyPpmqvQqnFuc4pu0Wr6tqTtVsz1RgF-0C0DOP-yk&v=1&r=https%3a%2f%2fwww.bing.com%2fsearch%3fq%3d%25e5%258f%25b0%25e5%25bd%25a2%2b%25e4%25b8%258a%25e5%25ba%2595&p=DevEx,5301.1"}, {"text": "福岡県中間市上底井野315-2", "displayText": "福岡県中間市上底井野315-2", "webSearchUrl": "https:\/\/www.bing.com\/cr?IG=0E1F17A8DE2343DCB81E5D3743307894&CID=01B2A43517346081302FADF6162661E7&rd=1&h=xn-OCbFnXvxU3H6GAPSkjK31kV297QQqy67P9CpG_fI&v=1&r=https%3a%2f%2fwww.bing.com%2fsearch%3fq%3d%25e7%25a6%258f%25e5%25b2%25a1%25e7%259c%258c%25e4%25b8%25ad%25e9%2596%2593%25e5%25b8%2582%25e4%25b8%258a%25e5%25ba%2595%25e4%25ba%2595%25e9%2587%258e315-2&p=DevEx,5302.1"}, {"text": "上底とは", "displayText": "上底とは", "webSearchUrl": "https:\/\/www.bing.com\/cr?IG=0E1F17A8DE2343DCB81E5D3743307894&CID=01B2A43517346081302FADF6162661E7&rd=1&h=6jN9XsksLm8CUtrXUz6R4KA_rMhGfas5dYuAsyBlP1M&v=1&r=https%3a%2f%2fwww.bing.com%2fsearch%3fq%3d%25e4%25b8%258a%25e5%25ba%2595%25e3%2581%25a8%25e3%2581%25af&p=DevEx,5303.1"}, {"text": "福岡県中間市上底井野", "displayText": "福岡県中間市上底井野", "webSearchUrl": "https:\/\/www.bing.com\/cr?IG=0E1F17A8DE2343DCB81E5D3743307894&CID=01B2A43517346081302FADF6162661E7&rd=1&h=M01w0MHlcBkRpE6FNnhyhphr43z607bYK3iujyy-Uu8&v=1&r=https%3a%2f%2fwww.bing.com%2fsearch%3fq%3d%25e7%25a6%258f%25e5%25b2%25a1%25e7%259c%258c%25e4%25b8%25ad%25e9%2596%2593%25e5%25b8%2582%25e4%25b8%258a%25e5%25ba%2595%25e4%25ba%2595%25e9%2587%258e&p=DevEx,5304.1"}, {"text": "台形の上底の求め方", "displayText": "台形の上底の求め方", "webSearchUrl": "https:\/\/www.bing.com\/cr?IG=0E1F17A8DE2343DCB81E5D3743307894&CID=01B2A43517346081302FADF6162661E7&rd=1&h=KrxYVR5lgDytk7iE1Z5v6_noMAQnFKFGgYkOpe521w0&v=1&r=https%3a%2f%2fwww.bing.com%2fsearch%3fq%3d%25e5%258f%25b0%25e5%25bd%25a2%25e3%2581%25ae%25e4%25b8%258a%25e5%25ba%2595%25e3%2581%25ae%25e6%25b1%2582%25e3%2582%2581%25e6%2596%25b9&p=DevEx,5305.1"}]}, "rankingResponse": {"mainline": {"items": [{"answerType": "WebPages", "resultIndex": 0, "value": {"id": "https:\/\/api.cognitive.microsoft.com\/api\/v5\/#WebPages.0"}}, {"answerType": "WebPages", "resultIndex": 1, "value": {"id": "https:\/\/api.cognitive.microsoft.com\/api\/v5\/#WebPages.1"}}, {"answerType": "WebPages", "resultIndex": 2, "value": {"id": "https:\/\/api.cognitive.microsoft.com\/api\/v5\/#WebPages.2"}}, {"answerType": "WebPages", "resultIndex": 3, "value": {"id": "https:\/\/api.cognitive.microsoft.com\/api\/v5\/#WebPages.3"}}, {"answerType": "WebPages", "resultIndex": 4, "value": {"id": "https:\/\/api.cognitive.microsoft.com\/api\/v5\/#WebPages.4"}}, {"answerType": "WebPages", "resultIndex": 5, "value": {"id": "https:\/\/api.cognitive.microsoft.com\/api\/v5\/#WebPages.5"}}, {"answerType": "WebPages", "resultIndex": 6, "value": {"id": "https:\/\/api.cognitive.microsoft.com\/api\/v5\/#WebPages.6"}}, {"answerType": "WebPages", "resultIndex": 7, "value": {"id": "https:\/\/api.cognitive.microsoft.com\/api\/v5\/#WebPages.7"}}, {"answerType": "WebPages", "resultIndex": 8, "value": {"id": "https:\/\/api.cognitive.microsoft.com\/api\/v5\/#WebPages.8"}}, {"answerType": "WebPages", "resultIndex": 9, "value": {"id": "https:\/\/api.cognitive.microsoft.com\/api\/v5\/#WebPages.9"}}]}, "sidebar": {"items": [{"answerType": "RelatedSearches", "value": {"id": "https:\/\/api.cognitive.microsoft.com\/api\/v5\/#RelatedSearches"}}]}}}